pyCHomP-0.4.3.dist-info/DESCRIPTION.rst
pyCHomP-0.4.3.dist-info/METADATA
pyCHomP-0.4.3.dist-info/RECORD
pyCHomP-0.4.3.dist-info/WHEEL
pyCHomP-0.4.3.dist-info/metadata.json
pyCHomP-0.4.3.dist-info/top_level.txt
pychomp/Braids.py
pychomp/CondensationGraph.py
pychomp/ConleyMorseFibration.py
pychomp/DirectedAcyclicGraph.py
pychomp/DrawFibration.py
pychomp/InducedSubgraph.py
pychomp/Poset.py
pychomp/StronglyConnectedComponents.py
pychomp/TopologicalSort.py
pychomp/TransitiveClosure.py
pychomp/TransitiveReduction.py
pychomp/__init__.py
pychomp/_chomp.cpython-36m-darwin.so
