Metadata-Version: 2.0
Name: pyCHomP
Version: 0.4.3
Summary: CHomP (Computational Homology Project) Python Extension
Home-page: https://github.com/shaunharker/pyCHomP
Author: Shaun Harker
Author-email: shaun.harker@rutgers.edu
License: UNKNOWN
Download-URL: https://github.com/shaunharker/pyCHomP/archive/v0.4.tar.gz
Platform: UNKNOWN
Requires-Dist: scipy
Requires-Dist: matplotlib
Requires-Dist: numpy
Requires-Dist: graphviz
